openlineage/client/__init__.py
openlineage/client/client.py
openlineage/client/constants.py
openlineage/client/event_v2.py
openlineage/client/facet.py
openlineage/client/facet_v2.py
openlineage/client/facets.py
openlineage/client/filter.py
openlineage/client/generated/__init__.py
openlineage/client/generated/base.py
openlineage/client/generated/base_subset_dataset.py
openlineage/client/generated/catalog_dataset.py
openlineage/client/generated/column_lineage_dataset.py
openlineage/client/generated/data_quality_assertions_dataset.py
openlineage/client/generated/data_quality_metrics_dataset.py
openlineage/client/generated/data_quality_metrics_input_dataset.py
openlineage/client/generated/dataset_type_dataset.py
openlineage/client/generated/dataset_version_dataset.py
openlineage/client/generated/datasource_dataset.py
openlineage/client/generated/documentation_dataset.py
openlineage/client/generated/documentation_job.py
openlineage/client/generated/environment_variables_run.py
openlineage/client/generated/error_message_run.py
openlineage/client/generated/execution_parameters_run.py
openlineage/client/generated/external_query_run.py
openlineage/client/generated/extraction_error_run.py
openlineage/client/generated/input_statistics_input_dataset.py
openlineage/client/generated/job_dependencies_run.py
openlineage/client/generated/job_type_job.py
openlineage/client/generated/lifecycle_state_change_dataset.py
openlineage/client/generated/nominal_time_run.py
openlineage/client/generated/output_statistics_output_dataset.py
openlineage/client/generated/ownership_dataset.py
openlineage/client/generated/ownership_job.py
openlineage/client/generated/parent_run.py
openlineage/client/generated/processing_engine_run.py
openlineage/client/generated/schema_dataset.py
openlineage/client/generated/source_code_job.py
openlineage/client/generated/source_code_location_job.py
openlineage/client/generated/sql_job.py
openlineage/client/generated/storage_dataset.py
openlineage_python-1.42.1.dist-info/WHEEL
openlineage_python-1.42.1.dist-info/entry_points.txt
openlineage_python-1.42.1.dist-info/METADATA
openlineage_python-1.42.1.dist-info/RECORD
